<annotation>
	<folder>train</folder>
	<filename>38.jpeg</filename>
	<path>/home/arpitjain/Desktop/Code/tabxolabs/hat_detection/Tensorflow/workspace/images/train/38.jpeg</path>
	<source>
		<database>Unknown</database>
	</source>
	<size>
		<width>287</width>
		<height>175</height>
		<depth>3</depth>
	</size>
	<segmented>0</segmented>
	<object>
		<name>Mask</name>
		<pose>Unspecified</pose>
		<truncated>0</truncated>
		<difficult>0</difficult>
		<bndbox>
			<xmin>147</xmin>
			<ymin>73</ymin>
			<xmax>196</xmax>
			<ymax>116</ymax>
		</bndbox>
	</object>
	<object>
		<name>Mask</name>
		<pose>Unspecified</pose>
		<truncated>0</truncated>
		<difficult>0</difficult>
		<bndbox>
			<xmin>232</xmin>
			<ymin>38</ymin>
			<xmax>262</xmax>
			<ymax>61</ymax>
		</bndbox>
	</object>
	<object>
		<name>Mask</name>
		<pose>Unspecified</pose>
		<truncated>0</truncated>
		<difficult>0</difficult>
		<bndbox>
			<xmin>68</xmin>
			<ymin>59</ymin>
			<xmax>103</xmax>
			<ymax>90</ymax>
		</bndbox>
	</object>
	<object>
		<name>Mask</name>
		<pose>Unspecified</pose>
		<truncated>0</truncated>
		<difficult>0</difficult>
		<bndbox>
			<xmin>15</xmin>
			<ymin>43</ymin>
			<xmax>58</xmax>
			<ymax>80</ymax>
		</bndbox>
	</object>
	<object>
		<name>No-jacket</name>
		<pose>Unspecified</pose>
		<truncated>0</truncated>
		<difficult>0</difficult>
		<bndbox>
			<xmin>223</xmin>
			<ymin>68</ymin>
			<xmax>286</xmax>
			<ymax>171</ymax>
		</bndbox>
	</object>
	<object>
		<name>Helmet</name>
		<pose>Unspecified</pose>
		<truncated>0</truncated>
		<difficult>0</difficult>
		<bndbox>
			<xmin>129</xmin>
			<ymin>21</ymin>
			<xmax>207</xmax>
			<ymax>53</ymax>
		</bndbox>
	</object>
	<object>
		<name>Helmet</name>
		<pose>Unspecified</pose>
		<truncated>1</truncated>
		<difficult>0</difficult>
		<bndbox>
			<xmin>1</xmin>
			<ymin>8</ymin>
			<xmax>67</xmax>
			<ymax>37</ymax>
		</bndbox>
	</object>
	<object>
		<name>Helmet</name>
		<pose>Unspecified</pose>
		<truncated>1</truncated>
		<difficult>0</difficult>
		<bndbox>
			<xmin>229</xmin>
			<ymin>1</ymin>
			<xmax>285</xmax>
			<ymax>34</ymax>
		</bndbox>
	</object>
	<object>
		<name>Helmet</name>
		<pose>Unspecified</pose>
		<truncated>0</truncated>
		<difficult>0</difficult>
		<bndbox>
			<xmin>61</xmin>
			<ymin>22</ymin>
			<xmax>112</xmax>
			<ymax>50</ymax>
		</bndbox>
	</object>
</annotation>
